{"get":"venues","parameters":{"country":"Guatemala"},"errors":[],"results":46,"paging":{"current":1,"total":1},"response":[{"id":2437,"name":"Estadio Municipal Manuel Ariza","address":null,"city":"El Progreso, Jutiapa","country":"Guatemala","capacity":1500,"surface":"grass","image":"https:\/\/media-3.api-sports.io\/football\/venues\/2437.png"},{"id":2439,"name":"Estadio Juan Ram\u00f3n Ponce Way","address":null,"city":"San Pedro Carch\u00e1","country":"Guatemala","capacity":4406,"surface":"grass","image":"https:\/\/media.api-sports.io\/football\/venues\/2439.png"},{"id":2440,"name":"Estadio Municipal de Chimaltenango","address":"Calle del Estadio","city":"Chimaltenango","country":"Guatemala","capacity":1500,"surface":"grass","image":"https:\/\/media-3.api-sports.io\/football\/venues\/2440.png"},{"id":2441,"name":"Estadio Cementos Progreso","address":"15 Avenida 28-00, Zona 6, La Pedrera","city":"Ciudad de Guatemala","country":"Guatemala","capacity":17000,"surface":"grass","image":"https:\/\/media.api-sports.io\/football\/venues\/2441.png"},{"id":2442,"name":"Estadio Municipal Olimpia","address":"Barrio San Sebasti\u00e1n","city":"Jocot\u00e1n","country":"Guatemala","capacity":5000,"surface":"grass","image":"https:\/\/media-3.api-sports.io\/football\/venues\/2442.png"},{"id":2443,"name":"Estadio Dr. \u00d3scar Monterroso Izaguirre","address":null,"city":"Retalhuleu","country":"Guatemala","capacity":8000,"surface":"grass","image":"https:\/\/media.api-sports.io\/football\/venues\/2443.png"},{"id":2444,"name":"Estadio Marquesa de la Ensenada","address":"Highway 12N","city":"San Marcos","country":"Guatemala","capacity":11000,"surface":"grass","image":"https:\/\/media-3.api-sports.io\/football\/venues\/2444.png"},{"id":2445,"name":"Estadio La Asunci\u00f3n","address":null,"city":"Asunci\u00f3n Mita","country":"Guatemala","capacity":8000,"surface":"grass","image":"https:\/\/media-3.api-sports.io\/football\/venues\/2445.png"},{"id":2446,"name":"Estadio Julio Armando C\u00f3bar","address":"Highway 2N","city":"San Miguel Petapa","country":"Guatemala","capacity":10000,"surface":"artificial turf","image":"https:\/\/media-3.api-sports.io\/football\/venues\/2446.png"},{"id":2447,"name":"Estadio Jos\u00e9 Luis Ibarra","address":"Barrio seis de Noviembre","city":"Nueva Concepci\u00f3n","country":"Guatemala","capacity":3000,"surface":"grass","image":"https:\/\/media-3.api-sports.io\/football\/venues\/2447.png"},{"id":2448,"name":"Estadio Municipal de Santa Cruz del Quich\u00e9","address":null,"city":"Santa Cruz del Quich\u00e9","country":"Guatemala","capacity":3000,"surface":"grass","image":"https:\/\/media-3.api-sports.io\/football\/venues\/2448.png"},{"id":2449,"name":"Estadio Municipal de San Pedro Sacatep\u00e9quez","address":null,"city":"San Pedro Sacatep\u00e9quez","country":"Guatemala","capacity":4000,"surface":"artificial turf","image":"https:\/\/media-3.api-sports.io\/football\/venues\/2449.png"},{"id":2450,"name":"Estadio Municipal las Victorias","address":null,"city":"Sansare","country":"Guatemala","capacity":2500,"surface":"grass","image":"https:\/\/media-3.api-sports.io\/football\/venues\/2450.png"},{"id":2452,"name":"Estadio Xamb\u00e1","address":null,"city":"Solol\u00e1","country":"Guatemala","capacity":6000,"surface":"grass","image":"https:\/\/media.api-sports.io\/football\/venues\/2452.png"},{"id":2453,"name":"Estadio Municipal Carlos Salazar Hijo","address":"8a. Calle 2-60, Zona 2","city":"Mazatenango","country":"Guatemala","capacity":12000,"surface":"grass","image":"https:\/\/media.api-sports.io\/football\/venues\/2453.png"},{"id":2454,"name":"Estadio Revoluci\u00f3n USAC","address":"Calle Diagonal 19","city":"Ciudad de Guatemala","country":"Guatemala","capacity":8000,"surface":"grass","image":"https:\/\/media-3.api-sports.io\/football\/venues\/2454.png"},{"id":2455,"name":"Estadio Las Victorias","address":null,"city":"Chiquimula","country":"Guatemala","capacity":9000,"surface":"grass","image":"https:\/\/media-3.api-sports.io\/football\/venues\/2455.png"},{"id":2456,"name":"Estadio Pensativo","address":null,"city":"Antigua","country":"Guatemala","capacity":10000,"surface":"artificial turf","image":"https:\/\/media-3.api-sports.io\/football\/venues\/2456.png"},{"id":2457,"name":"Estadio Verapaz Jose Angel Rossi","address":null,"city":"Cob\u00e1n","country":"Guatemala","capacity":15000,"surface":"grass","image":"https:\/\/media.api-sports.io\/football\/venues\/2457.png"},{"id":2458,"name":"Estadio Los Cuchumatanes","address":"Highway 7W","city":"Huehuetenango","country":"Guatemala","capacity":5433,"surface":"grass","image":"https:\/\/media-3.api-sports.io\/football\/venues\/2458.png"},{"id":2459,"name":"Estadio Municipal de Sanarate","address":null,"city":"Sanarate","country":"Guatemala","capacity":8765,"surface":"grass","image":"https:\/\/media.api-sports.io\/football\/venues\/2459.png"},{"id":2460,"name":"Estadio David Cord\u00f3n Hichos","address":null,"city":"Guastatoya","country":"Guatemala","capacity":6789,"surface":"grass","image":"https:\/\/media-3.api-sports.io\/football\/venues\/2460.png"},{"id":2461,"name":"Estadio Municipal El Mor\u00f3n","address":null,"city":"Puerto Iztapa","country":"Guatemala","capacity":4876,"surface":"grass","image":"https:\/\/media-3.api-sports.io\/football\/venues\/2461.png"},{"id":2462,"name":"Estadio Municipal Santa Luc\u00eda","address":null,"city":"Malacat\u00e1n","country":"Guatemala","capacity":7000,"surface":"grass","image":"https:\/\/media.api-sports.io\/football\/venues\/2462.png"},{"id":2463,"name":"Estadio El Tr\u00e9bol","address":"7 Calle y 7A Avenida","city":"Ciudad de Guatemala","country":"Guatemala","capacity":11625,"surface":"grass","image":"https:\/\/media-3.api-sports.io\/football\/venues\/2463.png"},{"id":2464,"name":"Estadio Municipal Mateo Sicay Paz","address":"CA-2","city":"Siquinal\u00e1","country":"Guatemala","capacity":6543,"surface":"grass","image":"https:\/\/media-3.api-sports.io\/football\/venues\/2464.png"},{"id":2465,"name":"Estadio Mario Camposeco","address":"1a. Calle y 14 Avenida, Zona 3","city":"Quetzaltenango","country":"Guatemala","capacity":11200,"surface":"grass","image":"https:\/\/media-3.api-sports.io\/football\/venues\/2465.png"},{"id":3499,"name":"Estadio Las Flores","address":"1ra Calle 0-74","city":"Jalapa","country":"Guatemala","capacity":8000,"surface":"grass","image":"https:\/\/media-3.api-sports.io\/football\/venues\/3499.png"},{"id":3705,"name":"Estadio Polideportivo Santa Catarina Mita","address":"Llano de Chinchilla","city":"Santa Catarina Mita","country":"Guatemala","capacity":2500,"surface":"grass","image":"https:\/\/media-3.api-sports.io\/football\/venues\/3705.png"},{"id":3901,"name":"Estadio Nacional Mateo Flores","address":"11 Avenida","city":"Ciudad de Guatemala","country":"Guatemala","capacity":29950,"surface":"grass","image":"https:\/\/media-3.api-sports.io\/football\/venues\/3901.png"},{"id":7048,"name":"Estadio Israel Barrios","address":"Rivera de la Vega, Zone 6","city":"Coatepeque","country":"Guatemala","capacity":20000,"surface":"grass","image":"https:\/\/media.api-sports.io\/football\/venues\/7048.png"},{"id":7133,"name":"Estadio Municipal Santa Luc\u00eda Cotzumalguapa","address":null,"city":"Cotzumalguapa","country":"Guatemala","capacity":9000,"surface":"grass","image":"https:\/\/media.api-sports.io\/football\/venues\/7133.png"},{"id":7141,"name":"Estadio del Ej\u00e9rcito","address":"13 Avenida","city":"Ciudad de Guatemala","country":"Guatemala","capacity":12453,"surface":"grass","image":"https:\/\/media-3.api-sports.io\/football\/venues\/7141.png"},{"id":8598,"name":"Estadio Comunal de la Mesilla","address":"CA-1","city":"La Democracia, Huehuetenango","country":"Guatemala","capacity":3900,"surface":"grass","image":"https:\/\/media.api-sports.io\/football\/venues\/8598.png"},{"id":8599,"name":"Estadio Armando Barillas","address":null,"city":"Escuintla","country":"Guatemala","capacity":10000,"surface":"grass","image":"https:\/\/media.api-sports.io\/football\/venues\/8599.png"},{"id":8600,"name":"Estadio David Ord\u00f3\u00f1ez Bardales","address":"18 Avenida 3-37, Zona 3","city":"Zacapa","country":"Guatemala","capacity":8000,"surface":"grass","image":"https:\/\/media-3.api-sports.io\/football\/venues\/8600.png"},{"id":8601,"name":"Estadio Carlos Enrique M\u00e9rida Cardona","address":null,"city":"Santa Cruz Barillas","country":"Guatemala","capacity":3000,"surface":"grass","image":"https:\/\/media-3.api-sports.io\/football\/venues\/8601.png"},{"id":8602,"name":"Estadio Municipal Quirigua","address":null,"city":"Los Amates","country":"Guatemala","capacity":2500,"surface":"grass","image":"https:\/\/media.api-sports.io\/football\/venues\/8602.png"},{"id":8603,"name":"Estadio Municipal La Pasi\u00f3n","address":"Barrio La Esperanza","city":"Sayaxch\u00e9","country":"Guatemala","capacity":4000,"surface":"grass","image":"https:\/\/media-3.api-sports.io\/football\/venues\/8603.png"},{"id":8604,"name":"Estadio Municipal","address":"B\u00e1rcena","city":"Villa Nueva","country":"Guatemala","capacity":2000,"surface":"artificial turf","image":"https:\/\/media.api-sports.io\/football\/venues\/8604.png"},{"id":8605,"name":"Estadio Vicente Ar\u00e9valo","address":null,"city":"Puerto San Jos\u00e9","country":"Guatemala","capacity":1500,"surface":"grass","image":"https:\/\/media.api-sports.io\/football\/venues\/8605.png"},{"id":8606,"name":"Estadio Municipal Tec\u00fan Um\u00e1n","address":null,"city":"Ayutla","country":"Guatemala","capacity":3000,"surface":"grass","image":"https:\/\/media-3.api-sports.io\/football\/venues\/8606.png"},{"id":8607,"name":"Estadio Pedro Coronado Campo","address":null,"city":"La Gomera","country":"Guatemala","capacity":3000,"surface":"grass","image":"https:\/\/media-3.api-sports.io\/football\/venues\/8607.png"},{"id":8608,"name":"Estadio Guillermo Slowing","address":null,"city":null,"country":"Guatemala","capacity":12000,"surface":"grass","image":"https:\/\/media.api-sports.io\/football\/venues\/8608.png"},{"id":8609,"name":"Estadio Julio H\u00e9ctor Paz Castilla","address":null,"city":null,"country":"Guatemala","capacity":8000,"surface":"grass","image":"https:\/\/media-3.api-sports.io\/football\/venues\/8609.png"},{"id":18610,"name":"Marco Antonio Fi\u00f3n Castellanos","address":null,"city":null,"country":"Guatemala","capacity":2000,"surface":"grass","image":"https:\/\/media.api-sports.io\/football\/venues\/18610.png"}]}