{"get":"venues","parameters":{"country":"Ivory-Coast"},"errors":[],"results":8,"paging":{"current":1,"total":1},"response":[{"id":3421,"name":"Stade Robert Champroux","address":"Off Boulevard Loraine Marcory","city":"Abidjan","country":"Ivory-Coast","capacity":20000,"surface":"artificial turf","image":"https:\/\/media.api-sports.io\/football\/venues\/3421.png"},{"id":3422,"name":"Stade Henri Konan B\u00e9di\u00e9","address":null,"city":"Abengourou","country":"Ivory-Coast","capacity":3000,"surface":"grass","image":"https:\/\/media.api-sports.io\/football\/venues\/3422.png"},{"id":3423,"name":"Parc des Sports de Treichville","address":"Treichville","city":"Abidjan","country":"Ivory-Coast","capacity":4000,"surface":"artificial turf","image":"https:\/\/media-3.api-sports.io\/football\/venues\/3423.png"},{"id":3424,"name":"Stade de Bouak\u00e9 (Stade de la Paix)","address":null,"city":"Bouak\u00e9","country":"Ivory-Coast","capacity":35000,"surface":"grass","image":"https:\/\/media-3.api-sports.io\/football\/venues\/3424.png"},{"id":11551,"name":"Stade Municipal de Yamoussoukro","address":null,"city":"Yamoussoukro","country":"Ivory-Coast","capacity":6000,"surface":"grass","image":"https:\/\/media-3.api-sports.io\/football\/venues\/11551.png"},{"id":3426,"name":"Stade Auguste Denise","address":null,"city":"San P\u00e9dro","country":"Ivory-Coast","capacity":8000,"surface":"grass","image":"https:\/\/media.api-sports.io\/football\/venues\/3426.png"},{"id":3427,"name":"Stade Victor Biaka Boda","address":null,"city":"Ouragahio, Gagnoa","country":"Ivory-Coast","capacity":5000,"surface":"grass","image":"https:\/\/media.api-sports.io\/football\/venues\/3427.png"},{"id":4691,"name":"Stade Municipal de Daloa","address":null,"city":"Daloa","country":"Ivory-Coast","capacity":4000,"surface":"grass","image":"https:\/\/media-3.api-sports.io\/football\/venues\/4691.png"}]}